scrape_it_now/__init__.py
scrape_it_now/cli.py
scrape_it_now/index.py
scrape_it_now/scrape.py
scrape_it_now/helpers/__init__.py
scrape_it_now/helpers/http.py
scrape_it_now/helpers/identity.py
scrape_it_now/helpers/logging.py
scrape_it_now/helpers/monitoring.py
scrape_it_now/helpers/persistence.py
scrape_it_now/helpers/resources.py
scrape_it_now/helpers/threading.py
scrape_it_now/helpers/trie.py
scrape_it_now/models/indexed.py
scrape_it_now/models/message.py
scrape_it_now/models/scraped.py
scrape_it_now/models/state.py
scrape_it_now/persistence/azure_blob_storage.py
scrape_it_now/persistence/azure_queue_storage.py
scrape_it_now/persistence/azure_search.py
scrape_it_now/persistence/iblob.py
scrape_it_now/persistence/iqueue.py
scrape_it_now/persistence/isearch.py
scrape_it_now/persistence/local_disk.py
scrape_it_now/resources/ads-nl.txt
scrape_it_now-3.0.4.dist-info/LICENSE
scrape_it_now-3.0.4.dist-info/METADATA
scrape_it_now-3.0.4.dist-info/WHEEL
scrape_it_now-3.0.4.dist-info/entry_points.txt
scrape_it_now-3.0.4.dist-info/top_level.txt
scrape_it_now-3.0.4.dist-info/RECORD
