Metadata-Version: 2.1
Name: scrape-it-now
Version: 3.0.4
Summary: Web scraper made for AI and simplicity in mind. It runs as a CLI that can be parallelized and outputs high-quality markdown content.
Author-email: Clémence Lesné <clemence@lesne.pro>
Maintainer-email: Clémence Lesné <clemence@lesne.pro>
License:                                  Apache License
Project-URL: Homepage, https://github.com/clemlesne/scrape-it-now
Project-URL: Issues, https://github.com/clemlesne/scrape-it-now/issues
Project-URL: Repository, https://github.com/clemlesne/scrape-it-now
Keywords: web,scraper,markdown,ai,parallel,cli,automation,data-extraction,web-crawling,content-indexing
Classifier: Development Status :: 4 - Beta
Classifier: Intended Audience :: Developers
Classifier: License :: OSI Approved :: Apache Software License
Classifier: Operating System :: MacOS
Classifier: Operating System :: Microsoft :: Windows
Classifier: Operating System :: OS Independent
Classifier: Operating System :: POSIX :: Linux
Classifier: Operating System :: POSIX
Classifier: Programming Language :: Python :: 3.11
Classifier: Programming Language :: Python :: 3.12
Classifier: Programming Language :: Python :: 3.13
Classifier: Topic :: Internet :: WWW/HTTP :: Dynamic Content :: Content Management System
Classifier: Topic :: Internet :: WWW/HTTP :: Indexing/Search
Classifier: Topic :: System :: Archiving :: Backup
Classifier: Topic :: Text Processing :: Markup :: Markdown
Classifier: Topic :: Utilities
Classifier: Typing :: Typed
Requires-Python: >=3.11
License-File: LICENSE
Requires-Dist: aiodns~=3.2
Requires-Dist: aiofiles~=24.1
Requires-Dist: aiohttp~=3.10
Requires-Dist: aiojobs~=1.3
Requires-Dist: aiosqlite~=0.20
Requires-Dist: azure-identity~=1.17
Requires-Dist: azure-monitor-opentelemetry~=1.6
Requires-Dist: azure-search-documents~=11.6a0
Requires-Dist: azure-storage-blob~=12.22
Requires-Dist: azure-storage-queue~=12.11
Requires-Dist: click~=8.1
Requires-Dist: openai~=1.42
Requires-Dist: opentelemetry-instrumentation-aiohttp-client~=0.0a0
Requires-Dist: opentelemetry-instrumentation-httpx~=0.0a0
Requires-Dist: opentelemetry-instrumentation-openai~=0.0a0
Requires-Dist: opentelemetry-instrumentation-redis~=0.0a0
Requires-Dist: opentelemetry-instrumentation-sqlite3~=0.0a0
Requires-Dist: playwright~=1.46
Requires-Dist: pydantic~=2.8
Requires-Dist: pypandoc~=1.13
Requires-Dist: python-dotenv~=1.0
Requires-Dist: structlog~=24.4
Requires-Dist: tenacity~=9.0
Requires-Dist: tiktoken~=0.7
Requires-Dist: truststore~=0.10
Provides-Extra: dev
Requires-Dist: deptry~=0.19; extra == "dev"
Requires-Dist: pyinstaller~=6.11; extra == "dev"
Requires-Dist: pyright~=1.1; extra == "dev"
Requires-Dist: pytest-asyncio~=0.23; extra == "dev"
Requires-Dist: pytest-repeat~=0.9; extra == "dev"
Requires-Dist: pytest-xdist[psutil]~=3.6; extra == "dev"
Requires-Dist: pytest~=8.3; extra == "dev"
Requires-Dist: ruff~=0.6; extra == "dev"
